<?xml version="1.0" encoding="UTF-8"?>
<ejb-jar xmlns:xsi="http://www.w3.org/2001/XMLSchema-instance" xmlns="http://xmlns.jcp.org/xml/ns/javaee" xsi:schemaLocation="http://xmlns.jcp.org/xml/ns/javaee http://xmlns.jcp.org/xml/ns/javaee/ejb-jar_3_2.xsd" version="3.2">
  <display-name>EJBproyecto_uoct </display-name>
  <!--<ejb-client-jar>EJBproyecto_uoctClient.jar</ejb-client-jar>  -->
    <enterprise-beans>
    <session>
      <ejb-name>TemaForo</ejb-name>
      <local-home>proyecto_uoct.foro.model.TemaForoLocalHome</local-home>
      <local>proyecto_uoct.foro.model.TemaForoLocal</local>
      <ejb-class>proyecto_uoct.foro.model.TemaForoBean</ejb-class>
      <session-type>Stateless</session-type>
      <transaction-type>Container</transaction-type>
    </session>
    <session>
      <ejb-name>Foros</ejb-name>
      <local-home>proyecto_uoct.foro.model.ForosLocalHome</local-home>
      <local>proyecto_uoct.foro.model.ForosLocal</local>
      <ejb-class>proyecto_uoct.foro.model.ForosBean</ejb-class>
      <session-type>Stateless</session-type>
      <transaction-type>Container</transaction-type>
    </session>
    <session>
      <ejb-name>Reportaje</ejb-name>
      <local-home>proyecto_uoct.infoyrep.model.ReportajeLocalHome</local-home>
      <local>proyecto_uoct.infoyrep.model.ReportajeLocal</local>
      <ejb-class>proyecto_uoct.infoyrep.model.ReportajeBean</ejb-class>
      <session-type>Stateless</session-type>
      <transaction-type>Container</transaction-type>
    </session>
    <session>
      <ejb-name>Usuario</ejb-name>
      <local-home>proyecto_uoct.usuario.model.UsuarioLocalHome</local-home>
      <local>proyecto_uoct.usuario.model.UsuarioLocal</local>
      <ejb-class>proyecto_uoct.usuario.model.UsuarioBean</ejb-class>
      <session-type>Stateless</session-type>
      <transaction-type>Container</transaction-type>
    </session>
    <session>
      <ejb-name>Cliente</ejb-name>
      <local-home>proyecto_uoct.documentacion.model.ClienteLocalHome</local-home>
      <local>proyecto_uoct.documentacion.model.ClienteLocal</local>
      <ejb-class>proyecto_uoct.documentacion.model.ClienteBean</ejb-class>
      <session-type>Stateless</session-type>
      <transaction-type>Container</transaction-type>
    </session>
    <session>
      <ejb-name>Documento</ejb-name>
      <local-home>proyecto_uoct.documentacion.model.DocumentoLocalHome</local-home>
      <local>proyecto_uoct.documentacion.model.DocumentoLocal</local>
      <ejb-class>proyecto_uoct.documentacion.model.DocumentoBean</ejb-class>
      <session-type>Stateless</session-type>
      <transaction-type>Container</transaction-type>
    </session>
    <session>
      <ejb-name>EIV</ejb-name>
      <local-home>proyecto_uoct.EIV.model.EIVLocalHome</local-home>
      <local>proyecto_uoct.EIV.model.EIVLocal</local>
      <ejb-class>proyecto_uoct.EIV.model.EIVBean</ejb-class>
      <session-type>Stateless</session-type>
      <transaction-type>Container</transaction-type>
    </session>
    <session>
      <ejb-name>Proyecto</ejb-name>
      <local-home>proyecto_uoct.proyecto.model.ProyectoLocalHome</local-home>
      <local>proyecto_uoct.proyecto.model.ProyectoLocal</local>
      <ejb-class>proyecto_uoct.proyecto.model.ProyectoBean</ejb-class>
      <session-type>Stateless</session-type>
      <transaction-type>Container</transaction-type>
    </session>
    <session>
      <ejb-name>Recursos</ejb-name>
      <local-home>proyecto_uoct.reservas.model.RecursosLocalHome</local-home>
      <local>proyecto_uoct.reservas.model.RecursosLocal</local>
      <ejb-class>proyecto_uoct.reservas.model.RecursosBean</ejb-class>
      <session-type>Stateless</session-type>
      <transaction-type>Container</transaction-type>
    </session>
    <session>
      <ejb-name>InfoInstit</ejb-name>
      <local-home>proyecto_uoct.infoyrep.model.InfoInstitLocalHome</local-home>
      <local>proyecto_uoct.infoyrep.model.InfoInstitLocal</local>
      <ejb-class>proyecto_uoct.infoyrep.model.InfoInstitBean</ejb-class>
      <session-type>Stateless</session-type>
      <transaction-type>Container</transaction-type>
    </session>
    <session>
      <ejb-name>Perfil</ejb-name>
      <local-home>proyecto_uoct.usuario.model.PerfilLocalHome</local-home>
      <local>proyecto_uoct.usuario.model.PerfilLocal</local>
      <ejb-class>proyecto_uoct.usuario.model.PerfilBean</ejb-class>
      <session-type>Stateless</session-type>
      <transaction-type>Container</transaction-type>
    </session>
    <session>
      <ejb-name>Inventario</ejb-name>
      <local-home>proyecto_uoct.inventario.model.InventarioLocalHome</local-home>
      <local>proyecto_uoct.inventario.model.InventarioLocal</local>
      <ejb-class>proyecto_uoct.inventario.model.InventarioBean</ejb-class>
      <session-type>Stateless</session-type>
      <transaction-type>Container</transaction-type>
    </session>
    <session>
      <ejb-name>Ventas</ejb-name>
      <local-home>proyecto_uoct.ventas.model.VentasLocalHome</local-home>
      <local>proyecto_uoct.ventas.model.VentasLocal</local>
      <ejb-class>proyecto_uoct.ventas.model.VentasBean</ejb-class>
      <session-type>Stateless</session-type>
      <transaction-type>Container</transaction-type>
    </session>
    <session>
      <ejb-name>Mensaje</ejb-name>
      <local-home>proyecto_uoct.mensaje.model.MensajeLocalHome</local-home>
      <local>proyecto_uoct.mensaje.model.MensajeLocal</local>
      <ejb-class>proyecto_uoct.mensaje.model.MensajeBean</ejb-class>
      <session-type>Stateless</session-type>
      <transaction-type>Container</transaction-type>
    </session>
    <session>
      <ejb-name>Fallas</ejb-name>
      <local-home>proyecto_uoct.fallas.model.FallasLocalHome</local-home>
      <local>proyecto_uoct.fallas.model.FallasLocal</local>
      <ejb-class>proyecto_uoct.fallas.model.FallasBean</ejb-class>
      <session-type>Stateless</session-type>
      <transaction-type>Container</transaction-type>
    </session>
    <session>
      <ejb-name>EmpMant</ejb-name>
      <local-home>proyecto_uoct.EmpMant.model.EmpMantLocalHome</local-home>
      <local>proyecto_uoct.EmpMant.model.EmpMantLocal</local>
      <ejb-class>proyecto_uoct.EmpMant.model.EmpMantBean</ejb-class>
      <session-type>Stateless</session-type>
      <transaction-type>Container</transaction-type>
    </session>
    <session>
      <ejb-name>MantenedorSistemas</ejb-name>
      <local-home>proyecto_uoct.mantenedorSistemas.model.MantenedorSistemasLocalHome</local-home>
      <local>proyecto_uoct.mantenedorSistemas.model.MantenedorSistemasLocal</local>
      <ejb-class>proyecto_uoct.mantenedorSistemas.model.MantenedorSistemasBean</ejb-class>
      <session-type>Stateless</session-type>
      <transaction-type>Container</transaction-type>
    </session>
    <session>
      <ejb-name>MantenedorSubsistemas</ejb-name>
      <local-home>proyecto_uoct.mantenedorSubsistemas.model.MantenedorSubsistemasLocalHome</local-home>
      <local>proyecto_uoct.mantenedorSubsistemas.model.MantenedorSubsistemasLocal</local>
      <ejb-class>proyecto_uoct.mantenedorSubsistemas.model.MantenedorSubsistemasBean</ejb-class>
      <session-type>Stateless</session-type>
      <transaction-type>Container</transaction-type>
    </session>
    <session>
      <ejb-name>MantenedorDispositivos</ejb-name>
      <local-home>proyecto_uoct.mantenedorDispositivos.model.MantenedorDispositivosLocalHome</local-home>
      <local>proyecto_uoct.mantenedorDispositivos.model.MantenedorDispositivosLocal</local>
      <ejb-class>proyecto_uoct.mantenedorDispositivos.model.MantenedorDispositivosBean</ejb-class>
      <session-type>Stateless</session-type>
      <transaction-type>Container</transaction-type>
    </session>
  </enterprise-beans>
   <assembly-descriptor>
    <container-transaction>
      <method>
        <ejb-name>TemaForo</ejb-name>
        <method-name>*</method-name>
      </method>
      <trans-attribute>Required</trans-attribute>
    </container-transaction>
    <container-transaction>
      <method>
        <ejb-name>Foros</ejb-name>
        <method-name>*</method-name>
      </method>
      <trans-attribute>Required</trans-attribute>
    </container-transaction>
    <container-transaction>
      <method>
        <ejb-name>Reportaje</ejb-name>
        <method-name>*</method-name>
      </method>
      <trans-attribute>Required</trans-attribute>
    </container-transaction>
    <container-transaction>
      <method>
        <ejb-name>Usuario</ejb-name>
        <method-name>*</method-name>
      </method>
      <trans-attribute>Required</trans-attribute>
    </container-transaction>
    <container-transaction>
      <method>
        <ejb-name>Cliente</ejb-name>
        <method-name>*</method-name>
      </method>
      <trans-attribute>Required</trans-attribute>
    </container-transaction>
    <container-transaction>
      <method>
        <ejb-name>Documento</ejb-name>
        <method-name>*</method-name>
      </method>
      <trans-attribute>Required</trans-attribute>
    </container-transaction>
    <container-transaction>
      <method>
        <ejb-name>EIV</ejb-name>
        <method-name>*</method-name>
      </method>
      <trans-attribute>Required</trans-attribute>
    </container-transaction>
    <container-transaction>
      <method>
        <ejb-name>Proyecto</ejb-name>
        <method-name>*</method-name>
      </method>
      <trans-attribute>Required</trans-attribute>
    </container-transaction>
    <container-transaction>
      <method>
        <ejb-name>Recursos</ejb-name>
        <method-name>*</method-name>
      </method>
      <trans-attribute>Required</trans-attribute>
    </container-transaction>
    <container-transaction>
      <method>
        <ejb-name>InfoInstit</ejb-name>
        <method-name>*</method-name>
      </method>
      <trans-attribute>Required</trans-attribute>
    </container-transaction>
    <container-transaction>
      <method>
        <ejb-name>Perfil</ejb-name>
        <method-name>*</method-name>
      </method>
      <trans-attribute>Required</trans-attribute>
    </container-transaction>
    <container-transaction>
      <method>
        <ejb-name>Inventario</ejb-name>
        <method-name>*</method-name>
      </method>
      <trans-attribute>Required</trans-attribute>
    </container-transaction>
    <container-transaction>
      <method>
        <ejb-name>Ventas</ejb-name>
        <method-name>*</method-name>
      </method>
      <trans-attribute>Required</trans-attribute>
    </container-transaction>
    <container-transaction>
      <method>
        <ejb-name>Mensaje</ejb-name>
        <method-name>*</method-name>
      </method>
      <trans-attribute>Required</trans-attribute>
    </container-transaction>
    <container-transaction>
      <method>
        <ejb-name>Fallas</ejb-name>
        <method-name>*</method-name>
      </method>
      <trans-attribute>Required</trans-attribute>
    </container-transaction>
    <container-transaction>
      <method>
        <ejb-name>EmpMant</ejb-name>
        <method-name>*</method-name>
      </method>
      <trans-attribute>Required</trans-attribute>
    </container-transaction>
    <container-transaction>
      <method>
        <ejb-name>MantenedorSistemas</ejb-name>
        <method-name>*</method-name>
      </method>
      <trans-attribute>Required</trans-attribute>
    </container-transaction>
    <container-transaction>
      <method>
        <ejb-name>MantenedorSubsistemas</ejb-name>
        <method-name>*</method-name>
      </method>
      <trans-attribute>Required</trans-attribute>
    </container-transaction>
    <container-transaction>
      <method>
        <ejb-name>MantenedorDispositivos</ejb-name>
        <method-name>*</method-name>
      </method>
      <trans-attribute>Required</trans-attribute>
    </container-transaction>
  </assembly-descriptor>
</ejb-jar>